MANIFEST.in
README.rst
requirements.txt
setup.py
test-requirements.txt
bin/ec2audit
ec2audit/__init__.py
ec2audit/app.py
ec2audit/output.py
ec2audit/utils.py
ec2audit/yamlout.py
ec2audit.egg-info/PKG-INFO
ec2audit.egg-info/SOURCES.txt
ec2audit.egg-info/dependency_links.txt
ec2audit.egg-info/requires.txt
ec2audit.egg-info/top_level.txt