Metadata-Version: 1.0
Name: ec2audit
Version: 0.1.1
Summary: Dump all EC2 information to a folder suitable for version control
Home-page: http://github.com/SimpleFinance/ec2audit
Author: Cosmin Stejerean
Author-email: cosmin@offbytwo.com
License: Apache License 2.0
Platform: UNKNOWN
Classifier: Development Status :: 3 - Alpha
Classifier: Environment :: Console
Classifier: License :: OSI Approved :: Apache Software License
Classifier: Topic :: Utilities
